localnmf/__init__.py
localnmf/ca_utils.py
localnmf/regression_update.py
localnmf/superpixel_analysis_ring.py
localnmf/visualization.py
localnmf/constrained_ring/__init__.py
localnmf/constrained_ring/cnmf_e.py
localnmf/constrained_ring/nnls.py
localnmf/constrained_ring/setup.py
localnmf/constrained_ring/update_cdnmf_fast.py
rlocalnmf-0.0.4.dist-info/LICENSE
rlocalnmf-0.0.4.dist-info/METADATA
rlocalnmf-0.0.4.dist-info/WHEEL
rlocalnmf-0.0.4.dist-info/top_level.txt
rlocalnmf-0.0.4.dist-info/RECORD
