Metadata-Version: 2.1
Name: rlocalnmf
Version: 0.0.4
Summary: New implementation of localnmf with advanced background models and initialization options
Classifier: Programming Language :: Python :: 3
License-File: LICENSE
Requires-Dist: numpy
Requires-Dist: scipy
Requires-Dist: cvxpy
Requires-Dist: Cython
Requires-Dist: networkx
Requires-Dist: scikit-learn
Requires-Dist: torch
Requires-Dist: matplotlib
Requires-Dist: opencv-python
Requires-Dist: scikit-image
